xnat2jupyterhub/__init__.py
xnat2jupyterhub/auth.py
xnat2jupyterhub/hooks/__init__.py
xnat2jupyterhub/hooks/swarmspawner.py
xnat2jupyterhub-0.3.0.dist-info/LICENSE
xnat2jupyterhub-0.3.0.dist-info/METADATA
xnat2jupyterhub-0.3.0.dist-info/WHEEL
xnat2jupyterhub-0.3.0.dist-info/top_level.txt
xnat2jupyterhub-0.3.0.dist-info/RECORD
