Metadata-Version: 2.1
Name: xnat2jupyterhub
Version: 0.3.0
Summary: XNAT extensions for JupyterHub
Home-page: https://bitbucket.org/xnat-containers/xnat-jupyterhub
Author: Andrew Lassiter
Author-email: andrewl@wustl.edu
License: Simplified BSD
Platform: UNKNOWN
License-File: LICENSE
